{"provider_id":"66820","month":2,"num_visits":1}
{"provider_id":"93100","month":6,"num_visits":1}
{"provider_id":"56155","month":5,"num_visits":1}
{"provider_id":"25636","month":8,"num_visits":2}
{"provider_id":"56441","month":6,"num_visits":4}
{"provider_id":"33775","month":4,"num_visits":2}
{"provider_id":"59609","month":6,"num_visits":1}
{"provider_id":"47297","month":3,"num_visits":3}
{"provider_id":"4841","month":6,"num_visits":3}
{"provider_id":"90979","month":10,"num_visits":1}
{"provider_id":"19838","month":5,"num_visits":2}
{"provider_id":"20414","month":11,"num_visits":4}
{"provider_id":"9243","month":3,"num_visits":4}
{"provider_id":"77221","month":8,"num_visits":1}
{"provider_id":"88107","month":4,"num_visits":1}
{"provider_id":"88107","month":5,"num_visits":2}
{"provider_id":"40137","month":12,"num_visits":2}
{"provider_id":"61174","month":7,"num_visits":3}
{"provider_id":"34853","month":3,"num_visits":1}
{"provider_id":"85868","month":9,"num_visits":2}
{"provider_id":"34795","month":7,"num_visits":1}
{"provider_id":"67460","month":8,"num_visits":4}
{"provider_id":"75509","month":9,"num_visits":5}
{"provider_id":"8721","month":7,"num_visits":3}
{"provider_id":"85227","month":10,"num_visits":1}
{"provider_id":"21830","month":9,"num_visits":2}
{"provider_id":"98268","month":4,"num_visits":4}
{"provider_id":"16139","month":12,"num_visits":2}
{"provider_id":"6972","month":5,"num_visits":1}
{"provider_id":"65897","month":1,"num_visits":1}
{"provider_id":"75238","month":1,"num_visits":4}
{"provider_id":"87070","month":9,"num_visits":2}
{"provider_id":"52631","month":10,"num_visits":1}
{"provider_id":"73500","month":5,"num_visits":1}
{"provider_id":"93890","month":2,"num_visits":3}
{"provider_id":"13046","month":4,"num_visits":2}
{"provider_id":"39025","month":5,"num_visits":5}
{"provider_id":"57954","month":9,"num_visits":1}
{"provider_id":"92591","month":8,"num_visits":4}
{"provider_id":"80304","month":5,"num_visits":4}
{"provider_id":"12681","month":9,"num_visits":4}
{"provider_id":"73212","month":10,"num_visits":3}
{"provider_id":"49300","month":3,"num_visits":1}
{"provider_id":"56860","month":7,"num_visits":3}
{"provider_id":"50210","month":11,"num_visits":3}
{"provider_id":"87784","month":10,"num_visits":1}
{"provider_id":"42612","month":2,"num_visits":4}
{"provider_id":"84720","month":8,"num_visits":3}
{"provider_id":"84720","month":7,"num_visits":1}
{"provider_id":"99795","month":1,"num_visits":2}
{"provider_id":"76886","month":2,"num_visits":1}
{"provider_id":"95817","month":3,"num_visits":3}
{"provider_id":"12355","month":8,"num_visits":3}
{"provider_id":"58064","month":10,"num_visits":2}
