{"provider_id":"45558","month":4,"num_visits":1}
{"provider_id":"22331","month":5,"num_visits":1}
{"provider_id":"7120","month":2,"num_visits":1}
{"provider_id":"99407","month":10,"num_visits":1}
{"provider_id":"94997","month":1,"num_visits":2}
{"provider_id":"14077","month":9,"num_visits":1}
{"provider_id":"61785","month":9,"num_visits":1}
{"provider_id":"84223","month":6,"num_visits":2}
{"provider_id":"87645","month":7,"num_visits":1}
{"provider_id":"20240","month":2,"num_visits":1}
{"provider_id":"77221","month":10,"num_visits":3}
{"provider_id":"36912","month":4,"num_visits":1}
{"provider_id":"72693","month":2,"num_visits":3}
{"provider_id":"20108","month":5,"num_visits":1}
{"provider_id":"29868","month":12,"num_visits":4}
{"provider_id":"63629","month":3,"num_visits":1}
{"provider_id":"91052","month":1,"num_visits":1}
{"provider_id":"64896","month":9,"num_visits":1}
{"provider_id":"85231","month":9,"num_visits":1}
{"provider_id":"79025","month":5,"num_visits":2}
{"provider_id":"76261","month":1,"num_visits":3}
{"provider_id":"42305","month":1,"num_visits":2}
{"provider_id":"42305","month":8,"num_visits":1}
{"provider_id":"27612","month":7,"num_visits":5}
{"provider_id":"36866","month":1,"num_visits":2}
{"provider_id":"19302","month":5,"num_visits":3}
{"provider_id":"28871","month":11,"num_visits":2}
{"provider_id":"69834","month":7,"num_visits":2}
{"provider_id":"28710","month":7,"num_visits":2}
{"provider_id":"32198","month":11,"num_visits":3}
{"provider_id":"41280","month":1,"num_visits":1}
{"provider_id":"89596","month":4,"num_visits":2}
{"provider_id":"4434","month":11,"num_visits":1}
{"provider_id":"60809","month":6,"num_visits":6}
{"provider_id":"99454","month":5,"num_visits":2}
{"provider_id":"52377","month":11,"num_visits":4}
{"provider_id":"69806","month":7,"num_visits":1}
{"provider_id":"85156","month":8,"num_visits":6}
{"provider_id":"85156","month":9,"num_visits":2}
{"provider_id":"90871","month":8,"num_visits":1}
{"provider_id":"39911","month":5,"num_visits":1}
{"provider_id":"7875","month":9,"num_visits":2}
{"provider_id":"99979","month":2,"num_visits":2}
{"provider_id":"82718","month":8,"num_visits":6}
{"provider_id":"77368","month":6,"num_visits":1}
{"provider_id":"58188","month":1,"num_visits":3}
{"provider_id":"46410","month":11,"num_visits":3}
{"provider_id":"642","month":10,"num_visits":2}
{"provider_id":"83857","month":11,"num_visits":1}
{"provider_id":"10913","month":5,"num_visits":1}
{"provider_id":"22435","month":5,"num_visits":2}
{"provider_id":"23018","month":9,"num_visits":2}
{"provider_id":"13073","month":4,"num_visits":1}
{"provider_id":"36043","month":12,"num_visits":2}
{"provider_id":"4417","month":10,"num_visits":4}
{"provider_id":"22219","month":1,"num_visits":1}
{"provider_id":"83892","month":10,"num_visits":2}
{"provider_id":"5304","month":8,"num_visits":2}
{"provider_id":"54746","month":7,"num_visits":1}
{"provider_id":"67167","month":12,"num_visits":3}
{"provider_id":"47849","month":8,"num_visits":1}
{"provider_id":"22600","month":12,"num_visits":3}
{"provider_id":"12310","month":8,"num_visits":2}
{"provider_id":"22752","month":2,"num_visits":2}
